common_utils_py/__init__.py
common_utils_py/did.py
common_utils_py/exceptions.py
common_utils_py/agreements/__init__.py
common_utils_py/agreements/access_proof_sla_template.py
common_utils_py/agreements/access_sla_template.py
common_utils_py/agreements/compute_sla_template.py
common_utils_py/agreements/did_sales_template.py
common_utils_py/agreements/nft721_access_template.py
common_utils_py/agreements/nft721_sales_template.py
common_utils_py/agreements/nft_access_proof_template.py
common_utils_py/agreements/nft_access_template.py
common_utils_py/agreements/nft_sales_template.py
common_utils_py/agreements/nft_sales_with_access_template.py
common_utils_py/agreements/service_agreement.py
common_utils_py/agreements/service_agreement_condition.py
common_utils_py/agreements/service_agreement_template.py
common_utils_py/agreements/service_factory.py
common_utils_py/agreements/service_types.py
common_utils_py/agreements/utils.py
common_utils_py/data_store/__init__.py
common_utils_py/data_store/storage_base.py
common_utils_py/ddo/__init__.py
common_utils_py/ddo/constants.py
common_utils_py/ddo/ddo.py
common_utils_py/ddo/metadata.py
common_utils_py/ddo/public_key_base.py
common_utils_py/ddo/public_key_rsa.py
common_utils_py/ddo/service.py
common_utils_py/did_resolver/__init__.py
common_utils_py/did_resolver/did_resolver.py
common_utils_py/http_requests/__init__.py
common_utils_py/http_requests/requests_session.py
common_utils_py/metadata/__init__.py
common_utils_py/metadata/exceptions.py
common_utils_py/metadata/metadata.py
common_utils_py/metadata/metadata_provider.py
common_utils_py/oauth2/__init__.py
common_utils_py/oauth2/jwk_utils.py
common_utils_py/oauth2/token.py
common_utils_py/utils/__init__.py
common_utils_py/utils/crypto.py
common_utils_py/utils/keytransfer.py
common_utils_py/utils/mimc_constants.py
common_utils_py/utils/poseidon_constants.py
common_utils_py/utils/utilities.py
common_utils_py-1.0.4.dist-info/LICENSE
common_utils_py-1.0.4.dist-info/METADATA
common_utils_py-1.0.4.dist-info/NOTICE
common_utils_py-1.0.4.dist-info/WHEEL
common_utils_py-1.0.4.dist-info/top_level.txt
common_utils_py-1.0.4.dist-info/RECORD
